{
    "title": "\ud83d\udc40\ud83d\udc40\ud83d\udc40",
    "author": "GriffinObuffalo",
    "subreddit": "Republican",
    "rank": 436,
    "score": 1277,
    "upvote_ratio": 0.78,
    "num_comments (reported by reddit)": 196,
    "url": "https://i.redd.it/84k4u38h5rie1.jpeg",
    "id": "1iny1xi",
    "selftext": "",
    "comments": [
        {
            "author": "Tiaan",
            "body": "It's hilarious to me how Republicans view the average liberal as an angry trans woke person, when in reality trans people are a tiny fraction of the population....",
            "score": 97,
            "replies": [
                {
                    "author": "Low_Theory_2795",
                    "body": "National average, yes, but west coast cities: very dense populations. I recommend Eugene, OR if you care to test my point.",
                    "score": 18,
                    "replies": [
                        {
                            "author": "MoarMoneeey",
                            "body": "I live in a Hollywood and trans individuals are still very rare here so I am challenging the legitimacy of your statement",
                            "score": 5,
                            "replies": [
                                {
                                    "author": "Low_Theory_2795",
                                    "body": "lol, ok. As I said before, take a trip to Eugene, Portland, or Seattle.  Perhaps Weho should be your next stop, though.",
                                    "score": 1,
                                    "replies": []
                                }
                            ]
                        },
                        {
                            "author": "Tiaan",
                            "body": "It makes sense for people to live in areas where they feel safe and accepted",
                            "score": 17,
                            "replies": []
                        },
                        {
                            "author": "FerretOnReddit",
                            "body": "As an Oregonian, I can confirm",
                            "score": 12,
                            "replies": []
                        },
                        {
                            "author": "Meleesucks11",
                            "body": "Why are you guys making fun of young J.D Vance?",
                            "score": -9,
                            "replies": []
                        }
                    ]
                },
                {
                    "author": "somosextremos82",
                    "body": "![gif](giphy|U1aN4HTfJ2SmgB2BBK)",
                    "score": 5,
                    "replies": []
                },
                {
                    "author": "International-Ad3447",
                    "body": "why are you here when this is the republican subreddit you should be in r/democrats",
                    "score": 1,
                    "replies": [
                        {
                            "author": "KetBanger45",
                            "body": "Because it\u2019s good to not put yourself in an echo chamber and leave your views open to scrutiny by those you disagree with?",
                            "score": 27,
                            "replies": [
                                {
                                    "author": "MrKum0",
                                    "body": "Very based",
                                    "score": 5,
                                    "replies": []
                                }
                            ]
                        },
                        {
                            "author": "RickPar",
                            "body": "They have banned everyone who doesn't believe 100% of the liberal fantasy, so now they have to come to conservative subs to find someone to talk to. I find it quite humorous. I go to those subs to see how they argue with each other.",
                            "score": 8,
                            "replies": [
                                {
                                    "author": "justusethatname",
                                    "body": "It\u2019s good for a laugh, I would imagine, at the very least, but I still avoid them. Better for my sanity.",
                                    "score": 3,
                                    "replies": []
                                },
                                {
                                    "author": "International-Ad3447",
                                    "body": "Yep they just call everyone racist and facist all day",
                                    "score": 1,
                                    "replies": []
                                },
                                {
                                    "author": "wheeledjustice",
                                    "body": "r/conservative does the same but in reverse. I\u2019d get off your high horse.",
                                    "score": 1,
                                    "replies": [
                                        {
                                            "author": "RickPar",
                                            "body": "I've seen no evidence of this. In fact r/conservative has been loaded with liberal propaganda lately",
                                            "score": 2,
                                            "replies": [
                                                {
                                                    "author": "wheeledjustice",
                                                    "body": "Almost every post I see when I click through is \u201cFlair Only\u201d and they only flair people who agree with them. I\u2019m not saying r/democrats doesn\u2019t do the same thing although admittedly I haven\u2019t checked recently. Regardless it\u2019s a practice I\u2019m not fond of because it stifles any form of debate or real learning",
                                                    "score": 3,
                                                    "replies": [
                                                        {
                                                            "author": "RickPar",
                                                            "body": "I agree 100%",
                                                            "score": 2,
                                                            "replies": []
                                                        }
                                                    ]
                                                }
                                            ]
                                        }
                                    ]
                                }
                            ]
                        },
                        {
                            "author": "Tiaan",
                            "body": "The Democrats are spineless losers who only pander to their wealthy donors. Why would I be in that subreddit",
                            "score": 1,
                            "replies": []
                        }
                    ]
                },
                {
                    "author": "uskevinmc",
                    "body": "did actually say anything in this post? lol",
                    "score": 1,
                    "replies": []
                },
                {
                    "author": "Longjumping_Type_901",
                    "body": "Yet that ideology is often pushed on a majority of people through media and education institutions etc.",
                    "score": 0,
                    "replies": []
                }
            ]
        },
        {
            "author": "Open_Bee_6995",
            "body": "Do we really need to lower ourselves to their level?",
            "score": 27,
            "replies": []
        },
        {
            "author": "sinisterkyrin",
            "body": "Why can\u2019t we just be kind to people instead of judging them?",
            "score": 96,
            "replies": [
                {
                    "author": "wherethegr",
                    "body": "Being forced into participating in someone\u2019s sexual fetish non consensually is not kind.",
                    "score": 27,
                    "replies": [
                        {
                            "author": "None",
                            "body": "[deleted]",
                            "score": -4,
                            "replies": [
                                {
                                    "author": "wherethegr",
                                    "body": "The term for it is Autogynephilia.\n\n https://feministwiki.org/wiki/Autogynephilia",
                                    "score": -8,
                                    "replies": [
                                        {
                                            "author": "SnooPeripherals2495",
                                            "body": "Jesus Christ look at the sources they are either outdated or straight up kink sites if your gonna defend a point at least check your sources",
                                            "score": 19,
                                            "replies": [
                                                {
                                                    "author": "wherethegr",
                                                    "body": "If you enjoy taking the lord\u2019s name in vain and rainbow degeneracy there\u2019s a political party for that but it\u2019s not this one.\n\nEdit: Downvote brigade much?",
                                                    "score": -16,
                                                    "replies": [
                                                        {
                                                            "author": "SnooPeripherals2495",
                                                            "body": "Son you are misguided by those with power even the lord through his son jesus preached for forgiveness and tolerance I do not support the continuation and chemical of confused individuals. But what I don\u2019t support even more is using outdated or just down right improper sources to change narrative or spread misinformation. The references you link to are laughable at best. Be better he created you in his image so why tarnish it.",
                                                            "score": 10,
                                                            "replies": []
                                                        },
                                                        {
                                                            "author": "Charimia",
                                                            "body": "Don\u2019t force your religion down our throats either. Fucking hypocrite.",
                                                            "score": 3,
                                                            "replies": [
                                                                {
                                                                    "author": "wherethegr",
                                                                    "body": "Are y\u2019all key word searching it because you\u2019re afraid people will find out? \n\nOr did you decide to identify as a Republican and expect us to play along?",
                                                                    "score": 2,
                                                                    "replies": []
                                                                }
                                                            ]
                                                        }
                                                    ]
                                                }
                                            ]
                                        }
                                    ]
                                }
                            ]
                        }
                    ]
                },
                {
                    "author": "BigIronOnMyHip45-70",
                    "body": "Why can\u2019t people on the left stop calling for the genocide of Republicans?\n\n[https://youtu.be/3EI27Zszocs?si=H2YPaQs5UWX1Cw6](https://youtu.be/3EI27Zszocs?si=H2YPaQs5UWX1Cw6)\\_\n\nHere\u2019s a link to prove it happens, acknowledge it or don\u2019t, it\u2019s happening whether your brains can handle it or not. Bunch of misandrists.\n\nhttps://preview.redd.it/hhalenpxntje1.jpeg?width=750&format=pjpg&auto=webp&s=72430086a8d3b3295ecc0cfdb1fe3f413c417750\n\nFound the screenshot I took of the post!",
                    "score": -7,
                    "replies": [
                        {
                            "author": "91NA8",
                            "body": "Now I may not be as chronically online as others but I've spent at least some time on FB, Twitter, Instagram and Reddit and I can't recall anyone calling for the genocide of republicans",
                            "score": 44,
                            "replies": [
                                {
                                    "author": "FerretOnReddit",
                                    "body": "Literally go on r/Pics, I'm sure you'll find at least like 20 people calling for exactly that.",
                                    "score": 2,
                                    "replies": []
                                },
                                {
                                    "author": "BigIronOnMyHip45-70",
                                    "body": "Don\u2019t need to be chronically online, I\u2019m not and I\u2019ve seen many comments of vile people stating what I said. Here\u2019s an example of a comment I saw today that said: \u201cwe have voter registration, we need to start going door to door and painting their walls in Republican red matter\u201d. Essentially saying going door to door and blowing Republicans brains out, it\u2019s insane shit. Not just regular people but they\u2019ve called for this same shit for Trump (obviously) and any Republican official. I can try to find a link for you.",
                                    "score": -7,
                                    "replies": [
                                        {
                                            "author": "91NA8",
                                            "body": "I'm not saying they don't exist, of course they do. On both sides and in every corner of history. But I doubt they are as commonplace and rampant as you make it seem. Stop letting sensationlist news and a few comments here and there make you think a whole political group is genocidal",
                                            "score": 24,
                                            "replies": [
                                                {
                                                    "author": "BigIronOnMyHip45-70",
                                                    "body": "I dm\u2019d you a link as it\u2019s not letting me post it here, that\u2019s just a tiny little bit, if you explore a lot of extremely liberal/left subreddits it won\u2019t take long for you to find grotesque people. And of course there are bad people in any group but it\u2019s mostly Democrats and that\u2019s just a fact.",
                                                    "score": -11,
                                                    "replies": [
                                                        {
                                                            "author": "91NA8",
                                                            "body": "I would say \"most are democrat and that's a fact\". I am on both Democrat and Republican subreddits and don't see it",
                                                            "score": 20,
                                                            "replies": []
                                                        },
                                                        {
                                                            "author": "farfarfunk",
                                                            "body": "So not just an anectodal fallacy, but also with an anectode based on comments from people on the internet, on reddit, in niche subreddits. Plus the assumption that extremely liberal/left = democrat.\n\n\"and that's just a fact\"\n\nI'm sorry, but you do **not** know what a fact is.",
                                                            "score": 5,
                                                            "replies": []
                                                        }
                                                    ]
                                                }
                                            ]
                                        },
                                        {
                                            "author": "FerretOnReddit",
                                            "body": "I once saw a comment talking about how we should basically rig the voting system with a \"political knowledge test\" or some shit like that, except it would be rigged against Republicans. It's ironic, the Libtards call us Fascists, yet they are the ones acting like Fascists.",
                                            "score": 4,
                                            "replies": [
                                                {
                                                    "author": "BigIronOnMyHip45-70",
                                                    "body": "Oh 100%. They are exactly what they call us, projecting at its finest.",
                                                    "score": 1,
                                                    "replies": [
                                                        {
                                                            "author": "FerretOnReddit",
                                                            "body": "Yep. I've also seen people in this sub talking about how the Libtards want a full genocide of Republicans, like you were talking about I'm pretty sure.",
                                                            "score": 3,
                                                            "replies": [
                                                                {
                                                                    "author": "BigIronOnMyHip45-70",
                                                                    "body": "Yep, you may have seen what I said before but there was a post this guy made from the left calling for him and other democrats to use voter registration to find republicans, then go door to door killing them. Direct quote is \u201cpainting the walls Republican red matter\u201d. Post has since been deleted but there are more.",
                                                                    "score": 3,
                                                                    "replies": [
                                                                        {
                                                                            "author": "FerretOnReddit",
                                                                            "body": "Lol. Even if some Libtard tried showing up at my house, first they'd have to get past our dogs (red lab and mini schnauzer, enough to distract them), and then my veteran father.",
                                                                            "score": 2,
                                                                            "replies": [
                                                                                {
                                                                                    "author": "BigIronOnMyHip45-70",
                                                                                    "body": "Mini schnauzer is gonna do the most damage for sure lol.",
                                                                                    "score": 2,
                                                                                    "replies": [
                                                                                        {
                                                                                            "author": "FerretOnReddit",
                                                                                            "body": "Death from the ankles down. She's also the runt of the litter but good enough.",
                                                                                            "score": 2,
                                                                                            "replies": [
                                                                                                {
                                                                                                    "author": "BigIronOnMyHip45-70",
                                                                                                    "body": "She\u2019s gonna lead the charge while your veteran father starts blaring \u201cFortunate Sons\u201d in the background \ud83d\ude02.",
                                                                                                    "score": 2,
                                                                                                    "replies": [
                                                                                                        {
                                                                                                            "author": "FerretOnReddit",
                                                                                                            "body": "Nah he's not THAT old, he served in the 90s lol. Still a great song though.",
                                                                                                            "score": 2,
                                                                                                            "replies": [
                                                                                                                {
                                                                                                                    "author": "BigIronOnMyHip45-70",
                                                                                                                    "body": "I just turned 30 and I\u2019d blare that song if someone tried invading my home, I didn\u2019t mean cause he\u2019s old, it\u2019s just a good song to play to psyche out the home invader lol. Also respect to your father and everyone else who has served or is currently serving. I will always be grateful for our veterans and active duty \ud83e\udee1.",
                                                                                                                    "score": 2,
                                                                                                                    "replies": []
                                                                                                                }
                                                                                                            ]
                                                                                                        }
                                                                                                    ]
                                                                                                }
                                                                                            ]
                                                                                        }
                                                                                    ]
                                                                                }
                                                                            ]
                                                                        }
                                                                    ]
                                                                }
                                                            ]
                                                        }
                                                    ]
                                                }
                                            ]
                                        }
                                    ]
                                }
                            ]
                        },
                        {
                            "author": "Myheadhurts47",
                            "body": "GENOCIDE OF REPUBLICANS\ud83d\ude2d\ud83d\ude2d\ud83d\ude2d you\u2019re out of your fucking mind\ud83d\ude02",
                            "score": 17,
                            "replies": [
                                {
                                    "author": "BigIronOnMyHip45-70",
                                    "body": "I see deranged lefties calling for mass killings of Republicans a lot, who\u2019s out of who\u2019s mind? You and the rest of them? I\u2019d agree. Or you\u2019re just on that copium and choose not to acknowledge the violence and pure, seething hatred coming from the democratic people. Again I acknowledge that there\u2019s pieces of shit on both sides, but I have not seen a single Republican calling for people to go door to door and killing people, I\u2019ve seen many of those violent calls and similar ones from the left though. I can send you the same link I sent the other guy and that was just a little sip of what I\u2019ve seen.",
                                    "score": 4,
                                    "replies": [
                                        {
                                            "author": "Zealousideal-Top-958",
                                            "body": "You see just as many republicans calling for the killings of liberals or gay/trans people, it\u2019s not really a party specific problem cuz there\u2019s plenty of crazies on both sides",
                                            "score": 7,
                                            "replies": [
                                                {
                                                    "author": "BigIronOnMyHip45-70",
                                                    "body": "No, no I haven\u2019t at all. Worst I\u2019ve seen from a Republican is \u201cput them in a mental institution\u201d. Crazies on both sides but lefties take the cake by far.",
                                                    "score": -2,
                                                    "replies": [
                                                        {
                                                            "author": "Zealousideal-Top-958",
                                                            "body": "We can agree to disagree then, I\u2019m not seeing much on this subreddit besides blaming leftists for everything and making fun of them, I\u2019m glad I\u2019m not a part of either party because y\u2019all are ridiculous",
                                                            "score": 5,
                                                            "replies": [
                                                                {
                                                                    "author": "BigIronOnMyHip45-70",
                                                                    "body": "Making fun of insane and completely delusional people yes. Making fun of the violent, unhinged ridiculousness from the left absolutely see that a lot.",
                                                                    "score": 0,
                                                                    "replies": [
                                                                        {
                                                                            "author": "Zealousideal-Top-958",
                                                                            "body": "Yeah I get that making fun of people different from yourself can be fun I just figured it would be a little more professional here seeing as to how it\u2019s the official republican Reddit but it still is reddit I suppose",
                                                                            "score": 1,
                                                                            "replies": [
                                                                                {
                                                                                    "author": "BigIronOnMyHip45-70",
                                                                                    "body": "Not making fun of them because they\u2019re simply \u201cdifferent\u201d. Making fun of them because they are fucking crazy as fuck living in their own pretend world filled with delusions and hypocrisy. You try to simplify it way too much lol.",
                                                                                    "score": -1,
                                                                                    "replies": [
                                                                                        {
                                                                                            "author": "Zealousideal-Top-958",
                                                                                            "body": "The way I see it you are most definitely making fun of people for being different because it makes you uncomfortable and that\u2019s fine but at least own up to it or have a valid reason for your criticism",
                                                                                            "score": 2,
                                                                                            "replies": [
                                                                                                {
                                                                                                    "author": "BigIronOnMyHip45-70",
                                                                                                    "body": "What? That\u2019s just a deluded thought. I don\u2019t give a fuck if someone is gay, suck all the dicks you want homie just not mine! The only time I\u2019ve made fun of a leftie is for insane delusional people, again, not just \u201ccause they\u2019re different\u201d. You\u2019re over-simplifying things again. \u201cThe way I see it\u201d translated to \u201cthe way I want to see it\u201d.",
                                                                                                    "score": 1,
                                                                                                    "replies": []
                                                                                                }
                                                                                            ]
                                                                                        }
                                                                                    ]
                                                                                }
                                                                            ]
                                                                        }
                                                                    ]
                                                                }
                                                            ]
                                                        }
                                                    ]
                                                }
                                            ]
                                        }
                                    ]
                                }
                            ]
                        },
                        {
                            "author": "Representative-Cut58",
                            "body": "this sounds very silly",
                            "score": 3,
                            "replies": []
                        },
                        {
                            "author": "Meleesucks11",
                            "body": "Can you provide a source to such a claim? Sorry but it sounds retarded.",
                            "score": 3,
                            "replies": []
                        },
                        {
                            "author": "wheeledjustice",
                            "body": "Genocide is a bit of an exaggeration in my experience but you\u2019re right in saying that death threats and wishing legitimate harm are far too prevalent. It\u2019s not just something the left does though. \n\nWhy can\u2019t the parties stop hating each other and learn how to cooperate?",
                            "score": 1,
                            "replies": [
                                {
                                    "author": "BigIronOnMyHip45-70",
                                    "body": "What else would you call it when someone literally says \u201cwe have voter registration, we can find the republicans and go door to door painting their walls Republican red matter (blowing their brains out)\u201d. That\u2019s calling for mass killings of one particular group, which is the definition of genocide. Lots of other death threats too. Thankfully Reddit mods banned that dude and the post is gone. There were replies of people agreeing and not a single person calling the poster out for inciting murder. Pathetic.",
                                    "score": 1,
                                    "replies": [
                                        {
                                            "author": "wheeledjustice",
                                            "body": "I didn\u2019t run across that guy. I\u2019ll give you the benefit of the doubt and assume that he existed because my god the internet is scary sometimes.",
                                            "score": 1,
                                            "replies": [
                                                {
                                                    "author": "BigIronOnMyHip45-70",
                                                    "body": "https://youtu.be/3EI27Zszocs?si=H2YPaQs5UWX1Cw6_\n\nHere\u2019s some more examples.",
                                                    "score": 1,
                                                    "replies": [
                                                        {
                                                            "author": "wheeledjustice",
                                                            "body": "That explains why I haven\u2019t seen it. I abandoned r/WhitePeopleTwitter when it became political instead of fun",
                                                            "score": 1,
                                                            "replies": [
                                                                {
                                                                    "author": "BigIronOnMyHip45-70",
                                                                    "body": "Yeah that sub is aggressive to say the least, and I\u2019m getting downvoted for stating facts lmao, it\u2019s Reddit though so, not surprised. Oh well, just cause they don\u2019t want to acknowledge the truth doesn\u2019t mean it didn\u2019t happen \ud83e\udd37\u200d\u2642\ufe0f.",
                                                                    "score": 1,
                                                                    "replies": [
                                                                        {
                                                                            "author": "wheeledjustice",
                                                                            "body": "I only go to political subs nowadays to see what both sides think on a political topic and make up my mind on the matter. I\u2019m only here today because Reddit decided I needed to be recommended this post lol. \n\nI live my truth, that\u2019s good enough for me. I\u2019ve learned to stop trying to challenge other\u2019s convictions unless they ask me to or if I think those convictions are legitimately harmful. The Live and Let Live approach",
                                                                            "score": 1,
                                                                            "replies": []
                                                                        }
                                                                    ]
                                                                }
                                                            ]
                                                        }
                                                    ]
                                                }
                                            ]
                                        }
                                    ]
                                }
                            ]
                        },
                        {
                            "author": "None",
                            "body": "[deleted]",
                            "score": -1,
                            "replies": [
                                {
                                    "author": "BigIronOnMyHip45-70",
                                    "body": "That\u2019s way more than cruel, that\u2019s domestic terrorist shit. Not saying I\u2019m not kind but it\u2019s just baffling how the same people who cheer inclusivity, tolerance, and love also want to literally red mist all Republicans.",
                                    "score": 10,
                                    "replies": [
                                        {
                                            "author": "TeaBaggerBoy",
                                            "body": "The left is the part of hypocrisy. It\u2019s on another level.",
                                            "score": 4,
                                            "replies": []
                                        }
                                    ]
                                },
                                {
                                    "author": "NinjaDom2113",
                                    "body": "Some?",
                                    "score": -2,
                                    "replies": [
                                        {
                                            "author": "sinisterkyrin",
                                            "body": "A lot? I\u2019ve also met republicans who were pretty awful too. \n\nThough, I\u2019ve seen it more in democrats.",
                                            "score": 6,
                                            "replies": [
                                                {
                                                    "author": "NinjaDom2113",
                                                    "body": "Obviously there are bad apples in every group. A vast majority of democrats are vile with very little sympathy for people other then anyone part of their hive mind.",
                                                    "score": 1,
                                                    "replies": []
                                                }
                                            ]
                                        }
                                    ]
                                }
                            ]
                        }
                    ]
                },
                {
                    "author": "TheGardiner",
                    "body": "I like you.",
                    "score": -4,
                    "replies": []
                },
                {
                    "author": "None",
                    "body": "[deleted]",
                    "score": -1,
                    "replies": [
                        {
                            "author": "sinisterkyrin",
                            "body": "Everyone should be kind no matter if you\u2019re Christian or not my friend.\n\nIf you\u2019re a Christian, your goal should be to spread love and compassion. I\u2019m not sure God would approve of you positing things like this, and having the attitude of: \u201cI should be rude to people because everyone\u2019s rude to me\u201d is a good thing.",
                            "score": 9,
                            "replies": []
                        }
                    ]
                }
            ]
        },
        {
            "author": "BeautifulLanguage335",
            "body": "Lmao I can\u2019t lie this is hilarious, but we really should be better. We don\u2019t need to snoop to their level and make fun of people. We can disagree but posts like these are going to prevent the other to being open to learn the truth",
            "score": 28,
            "replies": [
                {
                    "author": "TrulytheIdiot",
                    "body": "\u261d\ufe0f this",
                    "score": 3,
                    "replies": []
                },
                {
                    "author": "wheeledjustice",
                    "body": "Coming from someone who visits all kinds of subs, it\u2019s not just \u201ctheir\u201d level. Unless their just means hateful people on both sides.",
                    "score": 0,
                    "replies": [
                        {
                            "author": "BeautifulLanguage335",
                            "body": "No majority of hate is definitely from the left. Very popular with their cancel culture attitude. Plenty of jerks on the other side as well though. Overall, everyone can be better, but the left has time and time again shown their true colors",
                            "score": 1,
                            "replies": []
                        }
                    ]
                }
            ]
        },
        {
            "author": "TrustNo1378",
            "body": "![gif](giphy|ltIFdjNAasOwVvKhvx|downsized)",
            "score": 28,
            "replies": []
        },
        {
            "author": "Saigon2391",
            "body": "So dumb.",
            "score": 26,
            "replies": [
                {
                    "author": "aguywlthanopinion",
                    "body": "Salty lib",
                    "score": 0,
                    "replies": [
                        {
                            "author": "dafukisdis_1298",
                            "body": "Is this not part of the problem? On both sides? If anyone has a differing opinion, even if it\u2019s just on one thing, they\u2019re immediately a salty liberal. Or they\u2019re immediately a racist republican. \nWe can\u2019t alienate everyone who views things a little different and then wonder why people are liberal.",
                            "score": 4,
                            "replies": []
                        },
                        {
                            "author": "Saigon2391",
                            "body": "Whatever association in your head helps you internally cope.",
                            "score": 9,
                            "replies": [
                                {
                                    "author": "aguywlthanopinion",
                                    "body": "Cope with what man?",
                                    "score": -1,
                                    "replies": [
                                        {
                                            "author": "ambidextr_us",
                                            "body": "Cope with too much winning over the collective psychosis of liberals, apparently.",
                                            "score": 2,
                                            "replies": [
                                                {
                                                    "author": "aguywlthanopinion",
                                                    "body": "![gif](giphy|TCRIimkpZXoaEUiLEq)",
                                                    "score": 2,
                                                    "replies": []
                                                }
                                            ]
                                        }
                                    ]
                                }
                            ]
                        }
                    ]
                }
            ]
        },
        {
            "author": "Wiz101deathwiz",
            "body": "Hey democrats, if you want to win any more elections, maybe you don\u2019t want people like this as your poster child?",
            "score": 16,
            "replies": [
                {
                    "author": "YetiFlavourPotatoe",
                    "body": "What if we do ? Does that make me as degenerate as you ? Cause I sure would love to be in order to comprehend what's going on inside y'all's heads.",
                    "score": -26,
                    "replies": [
                        {
                            "author": "Space_Boss_393",
                            "body": "Keep losing elections then I guess, fine by me \ud83e\udd37\u200d\u2642\ufe0f",
                            "score": 15,
                            "replies": [
                                {
                                    "author": "FerretOnReddit",
                                    "body": "Vance 2028 and 2032\n\n\nTulsi 2036 and 2040",
                                    "score": 4,
                                    "replies": []
                                }
                            ]
                        },
                        {
                            "author": "LarryMyster",
                            "body": "Common Sense and Normalcy. Not weird stuff like screaming at the ocean from the beach lol. Like yall trying to summon aquaman? Don\u2019t answer that\u2026 wouldn\u2019t surprise me at this point. Lol",
                            "score": 10,
                            "replies": [
                                {
                                    "author": "MrNiceGuy304",
                                    "body": "Nothing screams common sense and normalcy more than beating the hell out of policeman and smearing shit on the walls of the Capitol Rotunda! Seems normal to me.",
                                    "score": 12,
                                    "replies": []
                                },
                                {
                                    "author": "Wiz101deathwiz",
                                    "body": "How dare you call him AquaMAN! That's assuming his gender, you dirty homophobe! /s",
                                    "score": 1,
                                    "replies": []
                                }
                            ]
                        }
                    ]
                }
            ]
        },
        {
            "author": "darkwolf523",
            "body": "Thought I was on r/bg3 for 2 seconds",
            "score": 2,
            "replies": []
        },
        {
            "author": "chodan9",
            "body": "You may not be able to look at a democrat and say \u201cthey are trans\u201d \n\nBut if you look at a trans person a safe bet would be to say \u201cthey are a democrat\u201d",
            "score": 2,
            "replies": [
                {
                    "author": "TheRoadRunner420",
                    "body": "Like Caitlyn Jenner?",
                    "score": 1,
                    "replies": [
                        {
                            "author": "chodan9",
                            "body": "I said safe bet, not sure bet lol",
                            "score": 1,
                            "replies": []
                        }
                    ]
                }
            ]
        },
        {
            "author": "diodeltrex",
            "body": "That's a typical reddit mod.",
            "score": 10,
            "replies": [
                {
                    "author": "GriffinObuffalo",
                    "body": "Well... I'm a Reddit mod and I'm not like that \ud83d\ude02\ud83d\ude02\ud83d\ude02",
                    "score": 7,
                    "replies": [
                        {
                            "author": "diodeltrex",
                            "body": "Yes but you're not a *typical* reddit mod \ud83d\ude09 Unfortunately everything else on this God forsaken site is controlled by people who ban you from a sub for wrong think.",
                            "score": 8,
                            "replies": [
                                {
                                    "author": "GriffinObuffalo",
                                    "body": "I hear ya brotha, we are hoping to eventually get some of that r/The_Donald energy and traffic here, and with the momentum we've got going in the country right now and guys like Zuckerberg being redpilled, hoping the Reddit Admins will just leave us TF alone here but, we'll see.",
                                    "score": 6,
                                    "replies": []
                                }
                            ]
                        },
                        {
                            "author": "TheGardiner",
                            "body": "Can I DM you about something wholly unrelated to this sub?",
                            "score": 0,
                            "replies": [
                                {
                                    "author": "GriffinObuffalo",
                                    "body": "Sure!",
                                    "score": 1,
                                    "replies": [
                                        {
                                            "author": "TheGardiner",
                                            "body": "So this is embarrassing, but i got banned from a huge sub like 7 or 8 months ago, for a reason I protest, and any attempt at appeal is just met with blanket muting. I dont know what to do or where else to appeal, no one will even reply to me. As the mod of a big sub, you must have some insight as to what to do in this situation.",
                                            "score": 1,
                                            "replies": [
                                                {
                                                    "author": "GriffinObuffalo",
                                                    "body": "Unfortunately there are just some mods that are complete psychos, that goes for Reddit and Facebook both, there's really nothing you can do about it other than just find better groups.",
                                                    "score": 1,
                                                    "replies": [
                                                        {
                                                            "author": "TheGardiner",
                                                            "body": "I hear you snd youre definitely right. 15 year user of this platform and this has never happened to me. Sub has 8M ppl.",
                                                            "score": 1,
                                                            "replies": []
                                                        }
                                                    ]
                                                }
                                            ]
                                        }
                                    ]
                                }
                            ]
                        }
                    ]
                },
                {
                    "author": "None",
                    "body": "lol \ud83d\ude01",
                    "score": 1,
                    "replies": []
                }
            ]
        },
        {
            "author": "None",
            "body": "[removed]",
            "score": 9,
            "replies": [
                {
                    "author": "GriffinObuffalo",
                    "body": "That'll never not be funny \ud83d\ude02",
                    "score": 2,
                    "replies": []
                }
            ]
        },
        {
            "author": "USAfirst_",
            "body": "\ud83e\udd23\ud83e\udd23\ud83e\udd23 this is so true",
            "score": 8,
            "replies": []
        },
        {
            "author": "MamaD79",
            "body": "OMG sad but true!",
            "score": 9,
            "replies": []
        },
        {
            "author": "iaminvisible1978",
            "body": "They want to follow your daughter in the bathroom.",
            "score": 6,
            "replies": [
                {
                    "author": "rainfalltsunami",
                    "body": "/r/notadragqueen",
                    "score": 4,
                    "replies": []
                }
            ]
        },
        {
            "author": "wherethegr",
            "body": "Boom",
            "score": 3,
            "replies": []
        },
        {
            "author": "Dirt_Illustrious",
            "body": "Lolz so on point",
            "score": 1,
            "replies": []
        },
        {
            "author": "None",
            "body": "I dare you to post this on a liberal page lol",
            "score": 1,
            "replies": []
        },
        {
            "author": "barkmagician",
            "body": "![gif](giphy|l0ExayQDzrI2xOb8A)",
            "score": 0,
            "replies": []
        },
        {
            "author": "sagittarius_90",
            "body": "\ud83d\ude02\ud83d\udcaf",
            "score": -2,
            "replies": []
        },
        {
            "author": "Dirty_Flacko",
            "body": "This just proves to me more we\u2019re living in a real world idiocracy since this is what people want to focus. Putting the other side down to just look as stupid or hateful as them. We need to be better as a society at whole and learn we\u2019re all just people who want the same things. To live life free without people and government telling us how to live, all have access to basic mean and needs of survival and life, opportunity to live the American dream with a good quality of life and raise your children off of more than just ramen and hamburger helper. This my side is right and your side is wrong is never going to heal this country only unity will and the will and want to have a great country. We don\u2019t make America great again because it already is great. We need to fix America to keep us better than great.",
            "score": 1,
            "replies": []
        },
        {
            "author": "leonard757",
            "body": "They\u2019ve turned angry when \u201ccancel culture\u201d was used against them \ud83e\udd14\ud83e\udd37\u200d\u2642\ufe0f",
            "score": 1,
            "replies": []
        },
        {
            "author": "wheeledjustice",
            "body": "As a prerequisite, I want to start by mentioning I\u2019m not rep or dem. So no calling me a libtard please. \n\nI just don\u2019t get why someone living in a way that makes them happy is a problem. This image just seems hateful towards someone because they don\u2019t fit the social norm. Can someone please explain the problem with being nonconformist?",
            "score": 1,
            "replies": []
        },
        {
            "author": "Fun-Bodybuilder8419",
            "body": "I can\u2019t tell if this is meant to be an insult or not\u00a0",
            "score": 1,
            "replies": []
        },
        {
            "author": "91NA8",
            "body": "Such a tolerant and welcoming group of individuals",
            "score": -1,
            "replies": [
                {
                    "author": "GriffinObuffalo",
                    "body": "We learned it from you.",
                    "score": 8,
                    "replies": [
                        {
                            "author": "91NA8",
                            "body": "Lol",
                            "score": -9,
                            "replies": []
                        }
                    ]
                }
            ]
        },
        {
            "author": "Upyourasshoesay",
            "body": "It\u2019s a democrat with severe mental illness who hates America, hates American values, hates the constitution and who wants to compete against women and be in women\u2019s locker rooms with severe mental illness.",
            "score": 0,
            "replies": []
        },
        {
            "author": "MrKeooo",
            "body": "Amazing hahaha",
            "score": -1,
            "replies": []
        },
        {
            "author": "CoinDexter101",
            "body": "Exactly!! \ud83d\udcaf",
            "score": 0,
            "replies": []
        },
        {
            "author": "redhood_714",
            "body": "LOLOL \ud83d\udc80\ud83d\udc80",
            "score": -2,
            "replies": []
        },
        {
            "author": "BillionaireBulletin",
            "body": "That\u2019s exactly right.",
            "score": 1,
            "replies": []
        },
        {
            "author": "MyDickKilledEpstein",
            "body": "I have actually met a trans person who supported Trump. Once you start assuming things based on appearance you become like the leftists. People who are obsessed with identity and how they are perceived rather than actual merit.",
            "score": 1,
            "replies": []
        },
        {
            "author": "searchparty2121",
            "body": "\ud83d\ude02",
            "score": -1,
            "replies": []
        }
    ]
}