{
    "title": "How Would You React to a Potential Partner Asking for Testing Prior to Intimacy?",
    "author": "_Aperture",
    "subreddit": "AskWomen",
    "rank": 15,
    "score": 126,
    "upvote_ratio": 0.93,
    "num_comments (reported by reddit)": 226,
    "url": "https://www.reddit.com/r/AskWomen/comments/1jckw7w/how_would_you_react_to_a_potential_partner_asking/",
    "id": "1jckw7w",
    "selftext": "Let\u2019s say you meet someone and enjoy a few dates together. How would you react to being asked to go get tested together before anything physical occurs?",
    "comments": [
        {
            "author": "Away-Classroom-3389",
            "body": "I\u2019d think they\u2019re responsible and don\u2019t wanna get stds",
            "score": 521,
            "replies": []
        },
        {
            "author": "cheeseandcrackers345",
            "body": "Sounds like a responsible human. I would happily get tested together with that person.",
            "score": 421,
            "replies": []
        },
        {
            "author": "celestialism",
            "body": "I have the same expectation and would have brought it up if they hadn\u2019t, so I would be relieved.",
            "score": 261,
            "replies": [
                {
                    "author": "itsbeenanhour",
                    "body": "I would be relieved that finally it wasn\u2019t me who had to bring it up.",
                    "score": 75,
                    "replies": [
                        {
                            "author": "celestialism",
                            "body": "Yeah, it\u2019s wild how many men put all the onus for that onto women. Like, aren\u2019t they worried about their own sexual health too?!",
                            "score": 20,
                            "replies": []
                        }
                    ]
                }
            ]
        },
        {
            "author": "Robokat_Brutus",
            "body": "We're going hand in hand as soon as possible.",
            "score": 163,
            "replies": []
        },
        {
            "author": "OooooorahNZ",
            "body": "I'd be relieved. You should get tested, and it would save me the effort of asking them to get checked out first. STD check on a new partner should be a normal part of a relationship process.\n\nI would not consider progressing sexually until this gets done.",
            "score": 143,
            "replies": []
        },
        {
            "author": "Individualchaotin",
            "body": "Very positive. \n\nI get regularly tested and wish straight men would do the same.",
            "score": 110,
            "replies": [
                {
                    "author": "bartturner",
                    "body": "Why only straight men?",
                    "score": -5,
                    "replies": [
                        {
                            "author": "LegitimatePirateMark",
                            "body": "She probably doesn\u2019t bang gay men.",
                            "score": 56,
                            "replies": []
                        },
                        {
                            "author": "Individualchaotin",
                            "body": "Because the majority of my gay friends gets regularly tested.",
                            "score": 11,
                            "replies": []
                        },
                        {
                            "author": "None",
                            "body": "[removed]",
                            "score": 3,
                            "replies": [
                                {
                                    "author": "AskWomen-ModTeam",
                                    "body": "Hello, /u/LycheeRoseSorbet!  **Please read this entire message before taking action.**\n\nYour comment has been removed:\n\nReplies to comments in /r/AskWomen should focus on and center the comment you're replying to while sticking to the original topic. Don't reply to someone else to talk about your opinion on their comment, your experience instead of theirs, to ask questions not inherently relevant to the question in the original post, debate them, or to offer unsolicited advice.\n\n\n\nHave questions about this moderator action? See the [AskWomen rules](http://www.reddit.com/r/askwomen/wiki/rules).\n\nIf you need assistance, first **copy a link to your removed post or comment** and then paste it in a message to the mod team [clicking here](http://www.reddit.com/message/compose/?to=/r/AskWomen&subject=Why+was+this+removed). We will not reply to messages without a link for review. DO NOT contact moderators privately. \n\n\n[AskWomen rules](http://www.reddit.com/r/askwomen/wiki/rules) | [AskWomen FAQ](http://www.reddit.com/r/askwomen/wiki/index)  \n[reddit rules](http://www.reddit.com/rules/) | [reddiquette](http://www.reddit.com/wiki/reddiquette)",
                                    "score": 1,
                                    "replies": []
                                }
                            ]
                        }
                    ]
                }
            ]
        },
        {
            "author": "babybottlepopz",
            "body": "Anyone that is turned off by this is a red flag and I wouldn\u2019t want to sleep with them anyways if they don\u2019t want to get tested with me.",
            "score": 94,
            "replies": []
        },
        {
            "author": "kaeorin",
            "body": "\"Sure, sounds good. Is there a clinic you recommend?\"\n\nI'd love it if they were the one to take care of arranging the appointments or whatever, because I'm just lazy enough that I never really get around to it, but if we're getting tested together, let's go for it.",
            "score": 621,
            "replies": [
                {
                    "author": "None",
                    "body": "[removed]",
                    "score": 1,
                    "replies": [
                        {
                            "author": "AskWomen-ModTeam",
                            "body": "Hello, /u/Aunt_Anne!  **Please read this entire message before taking action.**\n\nYour comment has been removed:\n\nReplies to comments in /r/AskWomen should focus on and center the comment you're replying to while sticking to the original topic. Don't reply to someone else to talk about your opinion on their comment, your experience instead of theirs, to ask questions not inherently relevant to the question in the original post, debate them, or to offer unsolicited advice.\n\n\n\nHave questions about this moderator action? See the [AskWomen rules](http://www.reddit.com/r/askwomen/wiki/rules).\n\nIf you need assistance, first **copy a link to your removed post or comment** and then paste it in a message to the mod team [clicking here](http://www.reddit.com/message/compose/?to=/r/AskWomen&subject=Why+was+this+removed). We will not reply to messages without a link for review. DO NOT contact moderators privately. \n\n\n[AskWomen rules](http://www.reddit.com/r/askwomen/wiki/rules) | [AskWomen FAQ](http://www.reddit.com/r/askwomen/wiki/index)  \n[reddit rules](http://www.reddit.com/rules/) | [reddiquette](http://www.reddit.com/wiki/reddiquette)",
                            "score": 2,
                            "replies": []
                        }
                    ]
                },
                {
                    "author": "None",
                    "body": "[removed]",
                    "score": 1,
                    "replies": [
                        {
                            "author": "AskWomen-ModTeam",
                            "body": "Hello, /u/MissesMarie79!  **Please read this entire message before taking action.**\n\nYour comment has been removed:\n\nReplies to comments in /r/AskWomen should focus on and center the comment you're replying to while sticking to the original topic. Don't reply to someone else to talk about your opinion on their comment, your experience instead of theirs, to ask questions not inherently relevant to the question in the original post, debate them, or to offer unsolicited advice.\n\n\n\nHave questions about this moderator action? See the [AskWomen rules](http://www.reddit.com/r/askwomen/wiki/rules).\n\nIf you need assistance, first **copy a link to your removed post or comment** and then paste it in a message to the mod team [clicking here](http://www.reddit.com/message/compose/?to=/r/AskWomen&subject=Why+was+this+removed). We will not reply to messages without a link for review. DO NOT contact moderators privately. \n\n\n[AskWomen rules](http://www.reddit.com/r/askwomen/wiki/rules) | [AskWomen FAQ](http://www.reddit.com/r/askwomen/wiki/index)  \n[reddit rules](http://www.reddit.com/rules/) | [reddiquette](http://www.reddit.com/wiki/reddiquette)",
                            "score": 1,
                            "replies": []
                        }
                    ]
                },
                {
                    "author": "None",
                    "body": "[removed]",
                    "score": 0,
                    "replies": [
                        {
                            "author": "AskWomen-ModTeam",
                            "body": "Hello, /u/Gellix!  **Please read this entire message before taking action.**\n\nYour comment has been removed:\n\nReplies to comments in /r/AskWomen should focus on and center the comment you're replying to while sticking to the original topic. Don't reply to someone else to talk about your opinion on their comment, your experience instead of theirs, to ask questions not inherently relevant to the question in the original post, debate them, or to offer unsolicited advice.\n\n\n\nHave questions about this moderator action? See the [AskWomen rules](http://www.reddit.com/r/askwomen/wiki/rules).\n\nIf you need assistance, first **copy a link to your removed post or comment** and then paste it in a message to the mod team [clicking here](http://www.reddit.com/message/compose/?to=/r/AskWomen&subject=Why+was+this+removed). We will not reply to messages without a link for review. DO NOT contact moderators privately. \n\n\n[AskWomen rules](http://www.reddit.com/r/askwomen/wiki/rules) | [AskWomen FAQ](http://www.reddit.com/r/askwomen/wiki/index)  \n[reddit rules](http://www.reddit.com/rules/) | [reddiquette](http://www.reddit.com/wiki/reddiquette)",
                            "score": 3,
                            "replies": []
                        }
                    ]
                },
                {
                    "author": "None",
                    "body": "[removed]",
                    "score": 0,
                    "replies": [
                        {
                            "author": "None",
                            "body": "[removed]",
                            "score": 2,
                            "replies": []
                        },
                        {
                            "author": "AskWomen-ModTeam",
                            "body": "Hello, /u/updown27!  **Please read this entire message before taking action.**\n\nYour comment has been removed:\n\nIn order to respect people's lived experiences, we do not allow invalidation of those experiences.\n\n\n\nHave questions about this moderator action? See the [AskWomen rules](http://www.reddit.com/r/askwomen/wiki/rules).\n\nIf you need assistance, first **copy a link to your removed post or comment** and then paste it in a message to the mod team [clicking here](http://www.reddit.com/message/compose/?to=/r/AskWomen&subject=Why+was+this+removed). We will not reply to messages without a link for review. DO NOT contact moderators privately. \n\n\n[AskWomen rules](http://www.reddit.com/r/askwomen/wiki/rules) | [AskWomen FAQ](http://www.reddit.com/r/askwomen/wiki/index)  \n[reddit rules](http://www.reddit.com/rules/) | [reddiquette](http://www.reddit.com/wiki/reddiquette)",
                            "score": 1,
                            "replies": []
                        }
                    ]
                },
                {
                    "author": "None",
                    "body": "[removed]",
                    "score": -5,
                    "replies": [
                        {
                            "author": "AskWomen-ModTeam",
                            "body": "Hello, /u/Winter_Value_7632!  **Please read this entire message before taking action.**\n\nYour comment has been removed:\n\nReplies to comments in /r/AskWomen should focus on and center the comment you're replying to while sticking to the original topic. Don't reply to someone else to talk about your opinion on their comment, your experience instead of theirs, to ask questions not inherently relevant to the question in the original post, debate them, or to offer unsolicited advice.\n\n\n\nHave questions about this moderator action? See the [AskWomen rules](http://www.reddit.com/r/askwomen/wiki/rules).\n\nIf you need assistance, first **copy a link to your removed post or comment** and then paste it in a message to the mod team [clicking here](http://www.reddit.com/message/compose/?to=/r/AskWomen&subject=Why+was+this+removed). We will not reply to messages without a link for review. DO NOT contact moderators privately. \n\n\n[AskWomen rules](http://www.reddit.com/r/askwomen/wiki/rules) | [AskWomen FAQ](http://www.reddit.com/r/askwomen/wiki/index)  \n[reddit rules](http://www.reddit.com/rules/) | [reddiquette](http://www.reddit.com/wiki/reddiquette)",
                            "score": 1,
                            "replies": []
                        }
                    ]
                }
            ]
        },
        {
            "author": "apostate456",
            "body": "Sounds like they have a healthy, adult concept about sexual health and physical intimacy.",
            "score": 56,
            "replies": []
        },
        {
            "author": "dear-mycologistical",
            "body": "I would be glad that they're being responsible.",
            "score": 37,
            "replies": []
        },
        {
            "author": "coffeeblossom",
            "body": "\"Sure! I'll buy lunch afterwards!\"",
            "score": 35,
            "replies": []
        },
        {
            "author": "alligatorprincess007",
            "body": "Relieved, because they likely asked that to past partners as well. Plus, now I don\u2019t have to bring it up.",
            "score": 29,
            "replies": []
        },
        {
            "author": "KBReadsALot",
            "body": "That's a valid thing to ask someone to do.",
            "score": 23,
            "replies": []
        },
        {
            "author": "Next-Ad3196",
            "body": "I asked my now husband this when we were dating. If he would have had any other reaction besides agreeing or understanding I would have run for the hills.",
            "score": 22,
            "replies": []
        },
        {
            "author": "MMMKAAyyyyy",
            "body": "I\u2019ve gotten tested with everyone that I\u2019ve slept with. I\u2019ve been with my husband now for 20 years and had 4 bf\u2019s before him. We waited 6 months bc HIV could take up to 6 months to show. \n\nIt was worth the wait. You get to know each other well beforehand. The sex is so much better. I can\u2019t orgasm with a condom on. I also can\u2019t come with someone I barely know.",
            "score": 58,
            "replies": [
                {
                    "author": "StarTrek_Recruitment",
                    "body": "Yup, I feel like this was the norm 20 some years ago.  Tested before getting intimate with my now husband as well (26years ago).",
                    "score": 5,
                    "replies": [
                        {
                            "author": "MMMKAAyyyyy",
                            "body": "They did a really great job of convincing me that HIV and other STI\u2019s were rampant and nobody cared enough to get tested. We were so fresh out of the Magic Johnson and other people dying of AIDS era.",
                            "score": 2,
                            "replies": []
                        }
                    ]
                }
            ]
        },
        {
            "author": "tawny-she-wolf",
            "body": "Sounds like common sense",
            "score": 19,
            "replies": []
        },
        {
            "author": "Lilith_Learned",
            "body": "I would be happily shocked. I\u2019m the only person to ever suggest this is my interactions.",
            "score": 15,
            "replies": []
        },
        {
            "author": "AlcoholYouLater97",
            "body": "Positively. I was the one to ask my ex to get tested before anything happened between us, and he had zero issues doing so. \n\nI expect any man to be tested prior to us being together, I respect the same ask from them.",
            "score": 13,
            "replies": []
        },
        {
            "author": "noonecaresat805",
            "body": "Honestly I would by more worried if they didn\u2019t. I know where I have been. I have no clue where they have been. I don\u2019t need to know with who or with how many people they have been with. But I do need to keep myself safe. So it\u2019s something I always asked for.  If they said no or got offended then I know that I wanted anything with them.",
            "score": 13,
            "replies": []
        },
        {
            "author": "Jell0h0h",
            "body": "Sounds like we're both going to get tested and thank goodness this person actually values their health and mine.",
            "score": 12,
            "replies": []
        },
        {
            "author": "Effective-Mongoose57",
            "body": "Massive green flag",
            "score": 12,
            "replies": []
        },
        {
            "author": "Amrick",
            "body": "Wish more men would ask this question first. I find that I am usually the one who brings it up. Their reaction is also very telling.",
            "score": 10,
            "replies": []
        },
        {
            "author": "thingsbetw1xt",
            "body": "I\u2019d be happy they brought it up so I didn\u2019t have to.",
            "score": 9,
            "replies": []
        },
        {
            "author": "antigoneelectra",
            "body": "If people are smart, they would all get tested when beginning a sexual relationship with a new partner and if they aren't exclusive.  It would be stupid not to.",
            "score": 7,
            "replies": []
        },
        {
            "author": "Mysterious-Novel-711",
            "body": "Thats 100% what you should be doing before any sex with anyone new. Safe and responsible, why tf would anyone open themselves uo to possible diseases.",
            "score": 6,
            "replies": []
        },
        {
            "author": "Hannah591",
            "body": "My boyfriend and I got tested, it wasn't an issue at all. I'd been celibate for 5 years but still did it for reassurance. I think it should be a standard practice for new couples.",
            "score": 7,
            "replies": []
        },
        {
            "author": "DarkField_SJ",
            "body": "I got myself tested for my first time with my fianc\u00e9, even though I was a virgin at the time. I wanted to trust him (so I asked him to show me results), but it wasn't fair for me to bypass the same request.",
            "score": 5,
            "replies": [
                {
                    "author": "StudioGhibliKat",
                    "body": "Same here. I got tested even though I knew I didn\u2019t have anything (virgin). He had no problem! He booked an appointment and showed me the results right on his online portal. (Didn\u2019t even have to ask for proof lol). \n\nI did NOT ask this because I wanted to go condom free\u2026 \nSTDs can still be transmitted through oral, skin contact, misused or broken condoms. I wasn\u2019t about to risk that just cuz we could use condoms.",
                    "score": 6,
                    "replies": []
                }
            ]
        },
        {
            "author": "The_Book-JDP",
            "body": "Sure lets go but I would totally do it for my own benefit since I've never had sex. Have to see if they are clean and did previous sexual intercourse safely.",
            "score": 5,
            "replies": []
        },
        {
            "author": "Out_of_the_Flames",
            "body": "\"Hey cool, I was going to ask you the same. Let's go together!\"",
            "score": 5,
            "replies": []
        },
        {
            "author": "Impressive-Yak-9726",
            "body": "It's a non-negotiable. If they won't, I'm not interested in moving forward.",
            "score": 4,
            "replies": []
        },
        {
            "author": "scaramouche123",
            "body": "I would love it. When I asked this before, partner got defensive and acted like I have something. For him it was such a weird concept to get tested. When my partner after that one came with this request, I was so happy.",
            "score": 4,
            "replies": []
        },
        {
            "author": "sea87",
            "body": "I always get tested after a breakup. It\u2019s not that hard - I message my dr, she orders tests and I drop in at the lab.",
            "score": 4,
            "replies": []
        },
        {
            "author": "CassRxs",
            "body": "I\u2019d be very relieved and would react positively that they\u2019d want to get tested before moving things further! This means they value my health and their own. I\u2019ve asked my husband this when we were dating and we both did it together :)",
            "score": 4,
            "replies": []
        },
        {
            "author": "Snoobeedo",
            "body": "Thrilled! I\u2019ve had a guy bring up the topic first, we both got tested and showed each other the printouts. It was awesome and from that point on we felt comfortable discussing anything.",
            "score": 5,
            "replies": []
        },
        {
            "author": "Conscious-Caramel-23",
            "body": "I'd feel glad they take their health seriously. I would worry about messing with anyone who would have a problem with this.",
            "score": 3,
            "replies": []
        },
        {
            "author": "appendixgallop",
            "body": "I would be pleased that I'd found someone with common sense.",
            "score": 3,
            "replies": []
        },
        {
            "author": "Minute_Wonder_4840",
            "body": "I would happily show my most recent results and ask them for theirs as well.",
            "score": 8,
            "replies": []
        },
        {
            "author": "heppapapu1",
            "body": "I would absolutely do it, no meed to react any more",
            "score": 3,
            "replies": []
        },
        {
            "author": "TernoftheShrew",
            "body": "I'd be relieved, as not only are they responsible, but care about both of our health enough to make that a priority.",
            "score": 3,
            "replies": []
        },
        {
            "author": "Bethechange1483",
            "body": "I would love that!",
            "score": 3,
            "replies": []
        },
        {
            "author": "kurious-katttt",
            "body": "I\u2019d feel great to not be the one asking all the time.",
            "score": 3,
            "replies": []
        },
        {
            "author": "CoeurDeSirene",
            "body": "honestly i'll probably bring up testing and sexual activity first. if they beat me to it, incredible! i'm very open about when i was tested and what kind of connections i've had with others since that last test. i keep results on my phone to show people and will not engage in any kind of \"naked\" play without having that conversation first.",
            "score": 3,
            "replies": []
        },
        {
            "author": "crimson_anemone",
            "body": "I did this with my now husband, upon my own request. Just think of the famous saying, *\"Better to be safe now than sorry later.\"*\n\nEdit: We were tested separately. He went to his urologist and I went to my ob. It's an uncomfortable process, but it was worth the piece of mind for both of us.",
            "score": 3,
            "replies": []
        },
        {
            "author": "Altostratus",
            "body": "I\u2019m non-monogamous, so it\u2019s standard practice for me to ask for recent test results before sleeping with someone.",
            "score": 3,
            "replies": []
        },
        {
            "author": "Larkfor",
            "body": "Green flag as long as we had been gearing up to being intimate and they didn't just ask out of nowhere/change the subject to sex out of nowhere.",
            "score": 3,
            "replies": []
        },
        {
            "author": "The_London_Badger",
            "body": "Both get tested, regularly. Like at least twice a year even in a relationship . Anyone that objects is not someone to be intimate with. Sexual health is important as any other health. It's a no brainer. It's not an infidelity or trust issue, it's a health issue. If they want you to, but they dont want to. That's a huge red flag. It's both or nothing. Every single girl that has refused to get tested, I've found out later had an std. I've had multiple women thank me cos my insistence led the doctor to picking up things they didn't know about.",
            "score": 3,
            "replies": []
        },
        {
            "author": "M2try4eq",
            "body": "Talking about testing status ought to be SOP. If you keep your paperwork after testing, all the better. One can also just decide that they'll test themselves afterwards and deal with the results.",
            "score": 3,
            "replies": []
        },
        {
            "author": "According_Coyote1078",
            "body": "This is what everyone should do, but few actually do",
            "score": 3,
            "replies": []
        },
        {
            "author": "house_of_mathoms",
            "body": "As someone who has partners lie about being tested just so they could (eventually) have unprotected sex with me having NEVER been tested because \"they didn't feel anything was wrong with them\" (found out about it a year later) yeah- not weird.  I \n\nSince then,  I made it a point to ask every man before I am intimate for evidence. Show me the results from LabCorps or whatever. I am happy to show mine.",
            "score": 3,
            "replies": []
        },
        {
            "author": "missvvvv",
            "body": "Very happy. Would go with them.",
            "score": 2,
            "replies": []
        },
        {
            "author": "BandicootMediocre844",
            "body": "I wouldn\u2019t mind . That\u2019s the adult thing to do .",
            "score": 2,
            "replies": []
        },
        {
            "author": "mailorderbridle",
            "body": "This is a good thing for me as I\u2019d expect potential partners to do the same.",
            "score": 2,
            "replies": []
        },
        {
            "author": "ChirpsMcPrime",
            "body": "I did a pull panel of testing before getting into a new relationship.  I didn't think I had anything, but wanted to know before going into a new relationship.  My current SO and I did end up having this talk, and it was a huge relief already having the tests done.  I would have done so anyway if I hadn't already.",
            "score": 2,
            "replies": []
        },
        {
            "author": "MachacaConHuevos",
            "body": "I would be impressed and would ask to see their most recent test results as well",
            "score": 2,
            "replies": []
        },
        {
            "author": "mtsle0329",
            "body": "I think it's only responsible.",
            "score": 2,
            "replies": []
        },
        {
            "author": "Gutinstinct999",
            "body": "I would be relieved",
            "score": 2,
            "replies": []
        },
        {
            "author": "ominoke",
            "body": "This should be the standard",
            "score": 2,
            "replies": []
        },
        {
            "author": "reijasunshine",
            "body": "It's my personal rule too, so I would be delighted if they brought it up first! Total green flag!",
            "score": 2,
            "replies": []
        },
        {
            "author": "Affectionate-Low5301",
            "body": "Sounds like someone who is proactive and responsible and I agree with this approach prior to intimacy and would tell him so.",
            "score": 2,
            "replies": []
        },
        {
            "author": "naanbud",
            "body": "Finally someone asked first!! It's a preference developing into a requirement for me, but it's not an easy thing to do (for me, at least). If someone did it first, I'd be relieved that they took on the burden/responsibility of and impressed by their respect for their sexual health.",
            "score": 2,
            "replies": []
        },
        {
            "author": "__Username__Taken___",
            "body": "Imo, it should be standard. Always ask for test results and share yours.",
            "score": 2,
            "replies": []
        },
        {
            "author": "BaylisAscaris",
            "body": "Good for them, but most tests don't catch most STIs, so I assume everyone has everything anyways and practice safer sex. Also get the HPV vaccine and ask if the testing includes HSV (they don't usually test for either in standard tests) because almost everyone already has them.",
            "score": 2,
            "replies": []
        },
        {
            "author": "Background_Dingo_561",
            "body": "I would love that. It\u2019s responsible and needed. So many STIs can stay dormant with no symptoms.",
            "score": 2,
            "replies": []
        },
        {
            "author": "lonelyterranaut",
            "body": "Pleased and would go to a clinic hand in hand.  I ask this before progressing to non-barrier penetration.",
            "score": 2,
            "replies": []
        },
        {
            "author": "xsahp",
            "body": "I find it so hot when a partner can have casual and responsible conversations about sex when not having sex. To this day, one of my most memorable interactions is with a guy who normalized op's scenario for me. I felt respected, cared for, and the directness of it all was very attractive",
            "score": 2,
            "replies": []
        },
        {
            "author": "Throwaya_1_18_24",
            "body": "Very positively!",
            "score": 2,
            "replies": []
        },
        {
            "author": "ikura-donburi",
            "body": "Major green flag. Someone taking the initiative first means it takes the pressure off me",
            "score": 2,
            "replies": []
        },
        {
            "author": "Hererabb",
            "body": "I'd be perfectly fine with it, in fact I'd probably be the one to ask first.",
            "score": 2,
            "replies": []
        },
        {
            "author": "updown27",
            "body": "This is my default. I always test before a new partner and expect them to test for me. I would not, however, get tested \"with\" them. That's very weird.",
            "score": 2,
            "replies": []
        },
        {
            "author": "chudeypatoodey",
            "body": "This is something I always do \ud83e\udd37\ud83c\udffe\u200d\u2640\ufe0f before anyone can touch me",
            "score": 2,
            "replies": [
                {
                    "author": "Brief-Reserve774",
                    "body": "Same",
                    "score": 1,
                    "replies": []
                }
            ]
        },
        {
            "author": "xtalcat_2",
            "body": "Can't use a condom? But yes, it's a wise thing to do once you decide to be exclusive. Not after a few dates.",
            "score": 2,
            "replies": []
        },
        {
            "author": "monkey3monkey2",
            "body": "Green flag.",
            "score": 2,
            "replies": []
        },
        {
            "author": "Due-Assistant9269",
            "body": "Sounds like a good idea. Don\u2019t want to get surprised.",
            "score": 2,
            "replies": []
        },
        {
            "author": "Empty-Elderberry-225",
            "body": "I'd be happy that they seem to take sexual health seriously and get tested together.",
            "score": 2,
            "replies": []
        },
        {
            "author": "goldandjade",
            "body": "Green flag, it means they\u2019re smart and responsible.",
            "score": 2,
            "replies": []
        },
        {
            "author": "gendered_nightmare",
            "body": "I would love this! This is my standard with any new partner",
            "score": 2,
            "replies": []
        },
        {
            "author": "Sufficient-Lock-2424",
            "body": "I would be very happy that they asked. Shows that they give a shit.",
            "score": 2,
            "replies": []
        },
        {
            "author": "Shpellaa",
            "body": "date ideas: let\u2019s go get tested and grab drinks",
            "score": 2,
            "replies": []
        },
        {
            "author": "Suleyco",
            "body": "Absolutely positively. I\u2019m usually the one suggesting this anyway.",
            "score": 2,
            "replies": []
        },
        {
            "author": "Altruistic-Put-5306",
            "body": "I would like it and I'll say I'll show you mine if you show me yours.",
            "score": 2,
            "replies": []
        },
        {
            "author": "mooobae",
            "body": "I would think that person is clean and respects Their body. Anyone who finds it offensive or rude probably has something",
            "score": 2,
            "replies": []
        },
        {
            "author": "xMissYanderex",
            "body": "Absolutely wouldn't mind, in fact, I'd feel much more comfortable if we both did.\n\nSafety is a must.",
            "score": 2,
            "replies": []
        },
        {
            "author": "Life_Ad1231",
            "body": "I work as a front desk receptionist as a urgent care and you would be surprised how many stds don\u2019t show symptoms in men so most of the time note never get tested and don\u2019t know. If they said they last person was clean or a virgin, go get tested. And you should anyways because people lie",
            "score": 2,
            "replies": []
        },
        {
            "author": "StarsandCats2Day",
            "body": "I would love it. And happily make a date of it! And be relieved that I wasn't the one who had to ask.",
            "score": 2,
            "replies": []
        },
        {
            "author": "SwankyLoompa",
            "body": "They'd want us to get tested together? Weird date idea but I'd be super down.",
            "score": 2,
            "replies": []
        },
        {
            "author": "BoohooKaChoo",
            "body": "Green flags all the way.",
            "score": 2,
            "replies": []
        },
        {
            "author": "ourhertz",
            "body": "It could be phrased weird but if nice I'd only appreciate it. \n\nI'd feel safer and like I was dating a responsible person.",
            "score": 2,
            "replies": []
        },
        {
            "author": "CanNotChangeName",
            "body": "Honestly? I'd respect them more. If you're scared to get tested, maybe you shouldn\u2019t be having sex in the first place imo",
            "score": 2,
            "replies": []
        },
        {
            "author": "xtrachubbykoala",
            "body": "It shows that they take their health seriously! We need to stop thinking of this as an insult.",
            "score": 2,
            "replies": []
        },
        {
            "author": "charmwatch",
            "body": "I would be thrilled that they are taking both mine and their sexual health into consideration, and happy we could have less risky sex after a good test outcome. Safe sex is very important to me. \n\nI am bi and I have asked new partners to test before. One girl loved that I suggested this, and said she felt safe with me because it made me seem careful and respectful of her body. \n\nA man agreed to test, and then didn\u2019t before the visit, but still hoped I would give him a blow job. Nope, gtfo my face \ud83d\ude00",
            "score": 2,
            "replies": []
        },
        {
            "author": "sponkinpice",
            "body": "Major green flag",
            "score": 2,
            "replies": []
        },
        {
            "author": "I_have_to_go_numba_3",
            "body": "I would be happy to do it. I asked my husband to get tested when we first started dating. We went separately and just shared our results when they came in.",
            "score": 2,
            "replies": []
        },
        {
            "author": "Global-Jellyfish-222",
            "body": "Sure thing jelly bean. It\u2019s a date to the clinic",
            "score": 2,
            "replies": []
        },
        {
            "author": "mtzmic",
            "body": "That is a great sign from my point of view. I generally had the same request when starting a new intimate relationship and I actually never had someone bring it up before I did. I would've been elated to have someone bring it up first for a change. It shows they are a responsible adult.",
            "score": 2,
            "replies": []
        },
        {
            "author": "Perfect-Resist5478",
            "body": "Good. You should do that for EVERY new partner. Why would you not??",
            "score": 2,
            "replies": [
                {
                    "author": "Brief-Reserve774",
                    "body": "My thought exactly",
                    "score": 1,
                    "replies": []
                }
            ]
        },
        {
            "author": "WimbledonWombleRep",
            "body": "Yeah alright. Good idea.",
            "score": 2,
            "replies": []
        },
        {
            "author": "Icy_Building_4492",
            "body": "Totally cool. I don\u2019t fuck without a test because safety. I\u2019m not trying to die due to some dirty Peter weeter.",
            "score": 1,
            "replies": []
        },
        {
            "author": "MarsupialObjective77",
            "body": "I would be very happy that they respect themselves and me enough to want to make sure we\u2019re both going to be safe moving forward intimately",
            "score": 1,
            "replies": []
        },
        {
            "author": "Odd-Opening-3158",
            "body": "Testing is free in Aus so why not.  However, If it's only been a few dates, I have to ask why he wants unprotected sex?  I mean, I'd prefer if that was something we did if we were in a long term, committed, serious relationsship and not the premise of the relationship.",
            "score": 3,
            "replies": [
                {
                    "author": "CoeurDeSirene",
                    "body": "you can still spread STIs through oral sex.",
                    "score": 9,
                    "replies": []
                },
                {
                    "author": "not_now_reddit",
                    "body": "Condoms break. It's still a good idea",
                    "score": 1,
                    "replies": []
                }
            ]
        },
        {
            "author": "None",
            "body": "[removed]",
            "score": 1,
            "replies": [
                {
                    "author": "AutoModerator",
                    "body": "Hello /u/Dizzy-Song-2797. **Please read this entire message before taking action.**\n\nYour post or comment has been removed because your Reddit Karma is too low to participate on AskWomen. You will be able to participate when your Karma has increased, you can do that by participating in good faith in other subreddits that don't have Karma requirements. This action **cannnot be undone** by the moderators.\n\n **No exceptions to this rule will be granted.** [Click here to read more about Reddit Karma](https://reddit.zendesk.com/hc/en-us/articles/204511829-What-is-karma-), and please also **[read our rules](https://www.reddit.com/r/AskWomen/wiki/rules) before participating**.\n\n\n*I am a bot, and this action was performed automatically. Please [contact the moderators of this subreddit](/message/compose/?to=/r/AskWomen) if you have any questions or concerns.*",
                    "score": 1,
                    "replies": []
                }
            ]
        },
        {
            "author": "Ok-Possible9327",
            "body": "It sounds like a mature and responsible conversation that has to be had before intimacy.  I am usually the one starting it, so I would be relieved to have someone else be the first one to bring it up for a change, tbh",
            "score": 1,
            "replies": []
        },
        {
            "author": "Left_Guess",
            "body": "I\u2019d be into it.",
            "score": 1,
            "replies": []
        },
        {
            "author": "Ticket2theMoon",
            "body": "I would think, \"Wow, what a conscience and communicative person, I feel so much safer with them now.\"",
            "score": 1,
            "replies": []
        },
        {
            "author": "Sana-Flower",
            "body": "That's always a turn on!",
            "score": 1,
            "replies": []
        },
        {
            "author": "serene_brutality",
            "body": "Every time I ask they take it like I\u2019m calling them promiscuous. So while intellectually most feel it\u2019s smart to ask, when they\u2019re asked they get seriously offended.",
            "score": 1,
            "replies": []
        },
        {
            "author": "chemrox409",
            "body": "Sure is better than safety gear",
            "score": 1,
            "replies": []
        },
        {
            "author": "MonstaB",
            "body": "I\u2019d be like wtf but also don\u2019t mind being tested. Unless it cost $1k per test then it\u2019ll be a problem",
            "score": 1,
            "replies": []
        },
        {
            "author": "ViolentPants",
            "body": "Relieving",
            "score": 1,
            "replies": []
        },
        {
            "author": "friskevision",
            "body": "I fully expect it. My last long term partner and I agreed to be tested before being intimate. In this day and age, I think it\u2019s a must. If someone doesn\u2019t agree, I wouldn\u2019t sleep with them.",
            "score": 1,
            "replies": []
        },
        {
            "author": "xvrcmpsmrcd",
            "body": "Sounds awesome!",
            "score": 1,
            "replies": []
        },
        {
            "author": "xxxSnowLillyxxx",
            "body": "Usually I'm the one that insists on this, so I'd be thrilled! There was one time a guy suggested it before I did, and it made me have so much respect for him.",
            "score": 1,
            "replies": []
        },
        {
            "author": "smooth_relation_744",
            "body": "No problems as long as they do it too.",
            "score": 1,
            "replies": []
        },
        {
            "author": "Ill_Sherbert1007",
            "body": "Fine with me. My partner got tested when I asked.",
            "score": 1,
            "replies": []
        },
        {
            "author": "2020grilledcheese",
            "body": "I\u2019d be glad that they said that because I would have requested it as well.",
            "score": 1,
            "replies": []
        },
        {
            "author": "themspriestitute",
            "body": "Responsible, I like it. I asked the same to the people I have been intimate with.",
            "score": 1,
            "replies": []
        },
        {
            "author": "panicpixiememegirl",
            "body": "I would love that because I'm the same.",
            "score": 1,
            "replies": []
        },
        {
            "author": "efra75",
            "body": "This used to be very common that you showed testing results at the start of a new relationship. Honestly not sure why it stopped when STIs are on the upswing. Not a bad policy",
            "score": 1,
            "replies": []
        },
        {
            "author": "spaceykait",
            "body": "When i was dating, i used to ask if people were recently tested or if they could be. Any time i had a new partner, i got tested. So it would be a welcome reprieve to have a partner ask first. It's part of being a responsible partner",
            "score": 1,
            "replies": []
        },
        {
            "author": "GummieLindsays",
            "body": "Honestly, I would respect it because it shows to me that he cares about being with the right person. He probably has a good track record with dating.\n\nIf he wants me to get tested, he better get tested himself for my own sake too.\n\nI think the next guy I'd see.... I would like to know what his recent results are as well. If he doesn't give them to me, I would prefer not to be with him.",
            "score": 1,
            "replies": []
        },
        {
            "author": "Unlikely_Race9177",
            "body": "I would be asking for the same.\u00a0",
            "score": 1,
            "replies": []
        },
        {
            "author": "Spiritual_One126",
            "body": "If anything, they\u2019re doing the right thing to be safe, and is going together. \n\n(They teach this kind of behaviour in safe sex ed\u2026 I learnt in university and as an adult, to my knowledge kids sex ed is still really bad).",
            "score": 1,
            "replies": []
        },
        {
            "author": "Cris_x",
            "body": "I think that would be a good idea and I wouldn't be mad or offended, safety first",
            "score": 1,
            "replies": []
        },
        {
            "author": "wannabe_wonder_woman",
            "body": "\"I'm so proud of you for being a reasonable person, what day and time works Best, we could go together.\"",
            "score": 1,
            "replies": []
        },
        {
            "author": "Will_V_S",
            "body": "I (f) have done testing. The guy asked me because he was a virgin. He knew I had lost my virginity from being raped 2 years before I met him. Even though I had a test after being raped, the virgin guy wanted proof I was clean. We both got tested together and found out our results together. We are both clean. \n\nEveryone should get tested, even if they aren't sexually active. You could have something and not know it until you are tested.",
            "score": 1,
            "replies": []
        },
        {
            "author": "624Seeds",
            "body": "Is this not the norm?",
            "score": 1,
            "replies": []
        },
        {
            "author": "3-rats-in-trenchcoat",
            "body": "Awesome af",
            "score": 1,
            "replies": []
        },
        {
            "author": "aytaytay_d",
            "body": "I have asked every single male I\u2019ve slept with. They all reacted positively and even considered it a turn on.",
            "score": 1,
            "replies": []
        },
        {
            "author": "TheEmpressDodo",
            "body": "After my divorce, that\u2019s the only way I\u2019d get intimate with someone. So, if they felt the same way, bonus points for maturity.",
            "score": 1,
            "replies": []
        },
        {
            "author": "KnockMeYourLobes",
            "body": "\"No problem. Is there someplace you recommend I go or is it OK if I go see my regular doctor?\"\n\nIt's not like it's a big deal. I would've gone if my boyfriend had asked and I'm sure he would've gone if I'd asked. But we'd both just gotten out of long term relationships (he was with his previous GF for 13 years and I was married for 24 before we got together) and neither one of us was worried about the other having anything.",
            "score": 1,
            "replies": []
        },
        {
            "author": "Warmbeachfeet",
            "body": "Not a problem.",
            "score": 1,
            "replies": []
        },
        {
            "author": "fictionalfirehazard",
            "body": "I think it's uncommon where I'm from, but I'd appreciate someone caring about both of our health",
            "score": 1,
            "replies": []
        },
        {
            "author": "None",
            "body": "[removed]",
            "score": 1,
            "replies": [
                {
                    "author": "AutoModerator",
                    "body": "Hello /u/Every-Protection-554. **Please read this entire message before taking action.**\n\nYour post or comment has been removed because your Reddit Karma is too low to participate on AskWomen. You will be able to participate when your Karma has increased, you can do that by participating in good faith in other subreddits that don't have Karma requirements. This action **cannnot be undone** by the moderators.\n\n **No exceptions to this rule will be granted.** [Click here to read more about Reddit Karma](https://reddit.zendesk.com/hc/en-us/articles/204511829-What-is-karma-), and please also **[read our rules](https://www.reddit.com/r/AskWomen/wiki/rules) before participating**.\n\n\n*I am a bot, and this action was performed automatically. Please [contact the moderators of this subreddit](/message/compose/?to=/r/AskWomen) if you have any questions or concerns.*",
                    "score": 1,
                    "replies": []
                }
            ]
        },
        {
            "author": "BitterSweetDesire",
            "body": "No issue at all. I'd be making sure hsv 2 and hpv were checked for on their part too. Non standard tests.",
            "score": 1,
            "replies": []
        },
        {
            "author": "MissPulpo",
            "body": "Is there any other way to react except being stoked that you're with a responsible human being who cares about their health and yours?",
            "score": 1,
            "replies": []
        },
        {
            "author": "StarTrek_Recruitment",
            "body": "Testing before intimacy with a new partner was pretty normal twenty odd years ago when I was dating. Is it not a common thing now?",
            "score": 1,
            "replies": []
        },
        {
            "author": "Mayday1019",
            "body": "Sounds like you have your next date planned!",
            "score": 1,
            "replies": []
        },
        {
            "author": "FrenchMoppit",
            "body": "Sounds like a smart & mature decision if you are gonna be putting your parts with someone else\u2019s parts\u2026I\u2019d want those parts to be clean and disease free.",
            "score": 1,
            "replies": []
        },
        {
            "author": "whatwhat612",
            "body": "Green flag! Show them my most recent test results and ask for theirs in exchange.",
            "score": 1,
            "replies": []
        },
        {
            "author": "CinderellasShoeHorn",
            "body": "Sure, we can go together.",
            "score": 1,
            "replies": []
        },
        {
            "author": "obamaschopsticks",
            "body": "That\u2019s completely normal. Should we go together?",
            "score": 1,
            "replies": []
        },
        {
            "author": "DaisyBryar",
            "body": "Had this happen when I was 21. Was surprised for a sec, sort of thought \"should I be offended?\", ultimately decided no and it was a responsible thing to ask.",
            "score": 1,
            "replies": []
        },
        {
            "author": "PrettyPet91",
            "body": "Happily. Immediate green flag.",
            "score": 1,
            "replies": []
        },
        {
            "author": "Paradise_Princess",
            "body": "I made my SO do a test before. We did a at-home test and I paid for it.",
            "score": 1,
            "replies": []
        },
        {
            "author": "ladyfox_9",
            "body": "I\u2019d love it. It\u2019s responsible and I\u2019d feel really safe with that person.",
            "score": 1,
            "replies": []
        },
        {
            "author": "peace_dabs",
            "body": "No problem! I have had no intimacy for a while and have tested negative for everything already.",
            "score": 1,
            "replies": []
        },
        {
            "author": "emu30",
            "body": "\u201cThank you for thinking of both of our safety!\u201d Green flag city",
            "score": 1,
            "replies": []
        },
        {
            "author": "AdAwkward1635",
            "body": "I\u2019d be okay shows me that they care",
            "score": 1,
            "replies": [
                {
                    "author": "AdAwkward1635",
                    "body": "But I\u2019d expect them to get tested as well",
                    "score": 1,
                    "replies": []
                }
            ]
        },
        {
            "author": "None",
            "body": "[removed]",
            "score": 1,
            "replies": [
                {
                    "author": "AutoModerator",
                    "body": "Hello /u/awithered. Thank you for participating in /r/AskWomen. **Please read this entire message before taking action.**\n\nYour submission has been removed, because your account does not have a verified email. **No exceptions will be granted**.\n\nYou can verify your email address on the [Reddit Preferences page](https://www.reddit.com/prefs/update/), and if you have any issues with verification please contact reddit support at /r/help. **Subreddit moderators do not have the tools to aid with verification**, so please ignore the bot in italics below, do not message the mod team about this as we have no way of helping you.\n\n\n*I am a bot, and this action was performed automatically. Please [contact the moderators of this subreddit](/message/compose/?to=/r/AskWomen) if you have any questions or concerns.*",
                    "score": 1,
                    "replies": []
                }
            ]
        },
        {
            "author": "dumbbitchcas",
            "body": "Why wouldn\u2019t they? I\u2019d ask.",
            "score": 1,
            "replies": []
        },
        {
            "author": "D-Spornak",
            "body": "I would be impressed that he was responsible and go do it.",
            "score": 1,
            "replies": []
        },
        {
            "author": "laughingpinkhues",
            "body": "Interesting question. I\u2019m always the one letting them know that there needs to be testing before we are intimate\u2026it\u2019s funny not sure how I would feel if it were the other way around lol. But then again that would never happen bc I will always be the one to bring it up first anyway. I also have a husband now so haven\u2019t had to deal with that in a long time",
            "score": 1,
            "replies": []
        },
        {
            "author": "RelevanceReverence",
            "body": "That's completely cool, I'll bring a print out, you bring yours \ud83d\udc4d\ud83c\udffb",
            "score": 1,
            "replies": []
        },
        {
            "author": "None",
            "body": "[removed]",
            "score": 1,
            "replies": [
                {
                    "author": "AutoModerator",
                    "body": "Hello /u/Glamour_Rabbit. **Please read this entire message before taking action.**\n\nYour post or comment has been removed because your Reddit Karma is too low to participate on AskWomen. You will be able to participate when your Karma has increased, you can do that by participating in good faith in other subreddits that don't have Karma requirements. This action **cannnot be undone** by the moderators.\n\n **No exceptions to this rule will be granted.** [Click here to read more about Reddit Karma](https://reddit.zendesk.com/hc/en-us/articles/204511829-What-is-karma-), and please also **[read our rules](https://www.reddit.com/r/AskWomen/wiki/rules) before participating**.\n\n\n*I am a bot, and this action was performed automatically. Please [contact the moderators of this subreddit](/message/compose/?to=/r/AskWomen) if you have any questions or concerns.*",
                    "score": 1,
                    "replies": []
                }
            ]
        },
        {
            "author": "Pixiestixwhore",
            "body": "I would happily get tested and even suggest we both get tested together",
            "score": 1,
            "replies": []
        },
        {
            "author": "PleasedPeas",
            "body": "Glad",
            "score": 1,
            "replies": []
        },
        {
            "author": "DolphinJew666",
            "body": "This is smart. As long as they're respectful about it, green flag",
            "score": 1,
            "replies": []
        },
        {
            "author": "kuroko72",
            "body": "Relieved, it means they're likely clean themselves if they're that worried and we can all confirm together.  I would expect they take a test with me though.  If they get insurance, I expect to be offered the same.  \n\nBut I would be surprised, it's never happened to me before.  But like, pleasantly surprised.",
            "score": 1,
            "replies": []
        },
        {
            "author": "PsychologicalClue6",
            "body": "I\u2019d be up for it, it\u2019s a reasonable request",
            "score": 1,
            "replies": []
        },
        {
            "author": "PDXFaeriePrincess",
            "body": "That would ensure my willingness to continue a relationship with that person, that\u2019s for sure.",
            "score": 1,
            "replies": []
        },
        {
            "author": "None",
            "body": "[removed]",
            "score": 1,
            "replies": [
                {
                    "author": "AutoModerator",
                    "body": "Hello /u/beehaving. Thank you for participating in /r/AskWomen. **Please read this entire message before taking action.**\n\nYour submission has been removed, because your account does not have a verified email. **No exceptions will be granted**.\n\nYou can verify your email address on the [Reddit Preferences page](https://www.reddit.com/prefs/update/), and if you have any issues with verification please contact reddit support at /r/help. **Subreddit moderators do not have the tools to aid with verification**, so please ignore the bot in italics below, do not message the mod team about this as we have no way of helping you.\n\n\n*I am a bot, and this action was performed automatically. Please [contact the moderators of this subreddit](/message/compose/?to=/r/AskWomen) if you have any questions or concerns.*",
                    "score": 1,
                    "replies": []
                }
            ]
        },
        {
            "author": "None",
            "body": "[removed]",
            "score": 1,
            "replies": [
                {
                    "author": "AutoModerator",
                    "body": "Hello /u/Sensitive_Jacket879. **Please read this entire message before taking action.**\n\nYour post or comment has been removed because your Reddit Karma is too low to participate on AskWomen. You will be able to participate when your Karma has increased, you can do that by participating in good faith in other subreddits that don't have Karma requirements. This action **cannnot be undone** by the moderators.\n\n **No exceptions to this rule will be granted.** [Click here to read more about Reddit Karma](https://reddit.zendesk.com/hc/en-us/articles/204511829-What-is-karma-), and please also **[read our rules](https://www.reddit.com/r/AskWomen/wiki/rules) before participating**.\n\n\n*I am a bot, and this action was performed automatically. Please [contact the moderators of this subreddit](/message/compose/?to=/r/AskWomen) if you have any questions or concerns.*",
                    "score": 1,
                    "replies": []
                }
            ]
        },
        {
            "author": "None",
            "body": "[removed]",
            "score": 1,
            "replies": [
                {
                    "author": "AutoModerator",
                    "body": "Hello /u/Funny_Monk_8865. **Please read this entire message before taking action.**\n\nYour post or comment has been removed because your Reddit Karma is too low to participate on AskWomen. You will be able to participate when your Karma has increased, you can do that by participating in good faith in other subreddits that don't have Karma requirements. This action **cannnot be undone** by the moderators.\n\n **No exceptions to this rule will be granted.** [Click here to read more about Reddit Karma](https://reddit.zendesk.com/hc/en-us/articles/204511829-What-is-karma-), and please also **[read our rules](https://www.reddit.com/r/AskWomen/wiki/rules) before participating**.\n\n\n*I am a bot, and this action was performed automatically. Please [contact the moderators of this subreddit](/message/compose/?to=/r/AskWomen) if you have any questions or concerns.*",
                    "score": 1,
                    "replies": []
                }
            ]
        },
        {
            "author": "imareemer",
            "body": "\u201cThis guy fucks\u201d",
            "score": 1,
            "replies": []
        },
        {
            "author": "Brief-Reserve774",
            "body": "I require the same so it would work quite well!",
            "score": 1,
            "replies": []
        },
        {
            "author": "RadicalNormy",
            "body": "I\u2019d be excited and happy I found a mature adult who wants to practice safe sex and clearly is into me enough to want to explore this together !",
            "score": 1,
            "replies": []
        },
        {
            "author": "SayuriKitsune",
            "body": "Sounds like a responsible adult, ill be fine with it, ill probably ask the same",
            "score": 1,
            "replies": []
        },
        {
            "author": "unearthmyself",
            "body": "I\u2019d be excited they mentioned it first so I didn\u2019t have to \ud83d\ude01",
            "score": 1,
            "replies": []
        },
        {
            "author": "adagioaddendum",
            "body": "I would be surprised I didn't bring it up first, then would schedule appointments. \n\nImmediate respect from me. It's also solid, up front proof that they care about both of our health and well-being.",
            "score": 1,
            "replies": []
        },
        {
            "author": "Sufficient-Sun11",
            "body": "No problem. We do it together.",
            "score": 1,
            "replies": []
        },
        {
            "author": "ponytailsandaviators",
            "body": "Would be great.",
            "score": 1,
            "replies": []
        },
        {
            "author": "None",
            "body": "[removed]",
            "score": 1,
            "replies": [
                {
                    "author": "AutoModerator",
                    "body": "Hello /u/PeachHarmonyy. **Please read this entire message before taking action.**\n\nYour post or comment has been removed because your Reddit Karma is too low to participate on AskWomen. You will be able to participate when your Karma has increased, you can do that by participating in good faith in other subreddits that don't have Karma requirements. This action **cannnot be undone** by the moderators.\n\n **No exceptions to this rule will be granted.** [Click here to read more about Reddit Karma](https://reddit.zendesk.com/hc/en-us/articles/204511829-What-is-karma-), and please also **[read our rules](https://www.reddit.com/r/AskWomen/wiki/rules) before participating**.\n\n\n*I am a bot, and this action was performed automatically. Please [contact the moderators of this subreddit](/message/compose/?to=/r/AskWomen) if you have any questions or concerns.*",
                    "score": 1,
                    "replies": []
                }
            ]
        },
        {
            "author": "BehindTheDoorway",
            "body": "I think they\u2019d be pretty responsible and I\u2019d love for us to get tested! This shouldn\u2019t be a taboo request. \n\nNot to mention, prior to intimacy is new in the relationship and you\u2019re getting to know one another still. It\u2019s okay to be safe!\n\nAnd like others said there would be a sense of relief since the other person brought up the subject first\u2764\ufe0f",
            "score": 1,
            "replies": []
        },
        {
            "author": "MimiPaw",
            "body": "The concept is great.  The \u201cgoing together\u201d part feels weird to me but that is just lack of experience.  I have not had many partners and there can be years long gaps between.  Having the panel run at my yearly pap appointment has been sufficient.  Is the testing usually offered at a walk in clinic?",
            "score": 1,
            "replies": []
        },
        {
            "author": "PaddlesOwnCanoe",
            "body": "I would say fair enough as long as I can see their test results as well.",
            "score": 1,
            "replies": []
        },
        {
            "author": "undercover_ace",
            "body": "This confuses me... wouldn't it be an issue if we didn't discuss it before sleeping together? I always bring it up beforehand cuz I'm not very interested in getting an std lol",
            "score": 1,
            "replies": [
                {
                    "author": "_Aperture",
                    "body": "Yes, this is referring to discussing and potentially going for testing prior to an intimate encounter together.",
                    "score": 1,
                    "replies": []
                }
            ]
        },
        {
            "author": "AnomalousAndFabulous",
            "body": "Wonderful! If a man asked me I would be thrilled. I\u2019m a lady who dates men.\n\nI do this with all my potential partners and I always have to lead with it, and sometimes I arrange it for them (if they don\u2019t have health insurance). \n\nIt weeds out the non serious partners and I remain STD free so there is no down side. Also I have had to say no after finding out people have various sexual health conditions they didn\u2019t know about before (and then had to treat to learn to live with it and not spread it).\n\nIf you\u2019re serious about someone you will want to protect them!",
            "score": 1,
            "replies": []
        },
        {
            "author": "LeoRose33",
            "body": "Massive GREEN flag. Shows common sense, thoughtfulness and care.\u00a0\n\nIf I mention it to someone, and they raise a fuss over it, it ain\u2019t happening",
            "score": 1,
            "replies": []
        },
        {
            "author": "Odd-Credit-7454",
            "body": "As a Gen Xer, this was 100% the norm when I was a younger adult. I became sexually active in the early years of the AIDS epidemic, and getting tested before sex was just part of the deal for anyone and everyone. I wouldn't think anything of this, aside from the fact that I'd be glad I didn't have to talk them into it or something.",
            "score": 1,
            "replies": []
        },
        {
            "author": "provocativecacti",
            "body": "i wouldn\u2019t be with them. i don\u2019t have an std and if they don\u2019t trust my word for it then i\u2019m not having sex with them. it\u2019s also extremely insulting",
            "score": -2,
            "replies": [
                {
                    "author": "dumbbitchcas",
                    "body": "It\u2019s insulting that they value their health?",
                    "score": 4,
                    "replies": []
                },
                {
                    "author": "Brief-Reserve774",
                    "body": "That\u2019s interesting, I make anyone I\u2019m intimate with test prior just in case. Trusting someone\u2019s word isn\u2019t worth risking your own health and safety and it\u2019s smarter to be safe and test just in case over trusting someone\u2019s word.",
                    "score": 1,
                    "replies": [
                        {
                            "author": "provocativecacti",
                            "body": "and i\u2019m not blaming you for that. i just personally find it insulting so i wouldn\u2019t sleep with that person",
                            "score": 1,
                            "replies": []
                        }
                    ]
                }
            ]
        },
        {
            "author": "Objective_Ad_6265",
            "body": "I would assume he is promiscous and be disgusted.",
            "score": -3,
            "replies": [
                {
                    "author": "dumbbitchcas",
                    "body": "Are you 12?",
                    "score": 4,
                    "replies": [
                        {
                            "author": "Objective_Ad_6265",
                            "body": "I'm just not promiscous to even consider I might hypotheticaly need STD test. And wouldn't want to date such person.",
                            "score": -3,
                            "replies": [
                                {
                                    "author": "dumbbitchcas",
                                    "body": "Are straight women just not afraid of aids?",
                                    "score": 2,
                                    "replies": [
                                        {
                                            "author": "Objective_Ad_6265",
                                            "body": "I don't do casual sex or sleep with people who do. I'm just not promiscous.",
                                            "score": -2,
                                            "replies": [
                                                {
                                                    "author": "dumbbitchcas",
                                                    "body": "You\u2019re very naive.",
                                                    "score": 5,
                                                    "replies": []
                                                },
                                                {
                                                    "author": "Brief-Reserve774",
                                                    "body": "Neither am I or anyone I\u2019ve ever slept with, but I still require testing prior because I\u2019m not risking my health and/or life. (Also there\u2019s more ways to catch things other than being promiscuous) be safe !",
                                                    "score": 1,
                                                    "replies": [
                                                        {
                                                            "author": "Objective_Ad_6265",
                                                            "body": "I know but it just feels wrong. To me it feels you must be promiscous or suspect the partner if you even hypotheticaly consider you might need to get tested. Unless you have reason to be safe if you get pricked by a needle or some other non sexual way.",
                                                            "score": 1,
                                                            "replies": []
                                                        }
                                                    ]
                                                }
                                            ]
                                        }
                                    ]
                                }
                            ]
                        }
                    ]
                }
            ]
        }
    ]
}