{
    "title": "Apartment in Japan",
    "author": "No_Chapter_4351",
    "subreddit": "malelivingspace",
    "rank": 7,
    "score": 131,
    "upvote_ratio": 1.0,
    "num_comments (reported by reddit)": 10,
    "url": "https://www.reddit.com/gallery/1je6ds7",
    "id": "1je6ds7",
    "selftext": "Hey everyone, this is the kitchen and living room of my first apartment and I would like to ask anyone for advice or ideas to improve it and make it more comfortable. Thank you in advance!",
    "comments": [
        {
            "author": "kirilw",
            "body": "Add warm light. The white/blueish light in the living room space makes it less cozy. Change the bulbs and add floor lamps with warm light bulbs.",
            "score": 15,
            "replies": []
        },
        {
            "author": "fjanon2021",
            "body": "I would swap tv and couch if possible. Move dining near kitchen and tv on other side means you can watch while you cook. More warm lights and some plants, it will look cozy.",
            "score": 7,
            "replies": [
                {
                    "author": "drunk-tusker",
                    "body": "Seriously OP why did you do this backwards from literally every Japanese LDK I\u2019ve ever seen?",
                    "score": 2,
                    "replies": []
                }
            ]
        },
        {
            "author": "ccoastmike",
            "body": "What a cute first apartment!  It\u2019s 100x better than my first ten apartments!\n\nI agree with the other commenter that some different lighting would really help.  The ceiling lights seem very cold / blue.  Other than that I think it just needs some personality.  Some color here and there.  Some pictures up on the walls.  All the usually stuff",
            "score": 4,
            "replies": []
        },
        {
            "author": "nosylittlebunny",
            "body": "I think a few plants, a pop of color here and there would make a whole lot of difference",
            "score": 3,
            "replies": []
        },
        {
            "author": "Mr_Stkrdknmibalz00",
            "body": "Nasubi, is that you?",
            "score": 2,
            "replies": [
                {
                    "author": "SlothySundaySession",
                    "body": "Could be!",
                    "score": 1,
                    "replies": []
                }
            ]
        },
        {
            "author": "Delicious_Ring2727",
            "body": "Living good for japanese standards as a single male in Tokyo\u00a0",
            "score": 2,
            "replies": []
        },
        {
            "author": "xyepxnopex",
            "body": "Put your microwave on the counter in between the stove and the sink. Run LED string plant grow lights on the inside top border of your baking shelf and fill with small succulents. Buy 2-4 telescopic standing grow lights of various heights and fill the surface where the microwave is now with additional plants of varying complimentary heights and types.\u00a0",
            "score": 1,
            "replies": []
        }
    ]
}